[{"Id":"bc13e7f9-bccb-4006-a77b-5dfd99827ddd","PatientDescription":"Disim agriyir","DrName":"Muradxan","PatientId":"4035fd9e-55a8-4b06-ac4e-741f7aba86eb","PatientName":"Eli","PatientSurname":"Veliyev","Room":{"Number":1,"RoomType":1,"IsEmty":true},"Price":200.0,"DoctorProfit":0.0,"Categoria":4,"DateBegin":"2021-01-25T23:41:01.5907638+04:00","DateEnd":"2021-01-25T23:45:00","UsingDevice":[],"Results":null,"UsingMedicine":[],"Recept":[],"Status":2,"Diagnosis":null},{"Id":"239ace02-6087-4962-8a05-aa4285efc4a0","PatientDescription":"Disim agriyir","DrName":"Muradxan","PatientId":"4035fd9e-55a8-4b06-ac4e-741f7aba86eb","PatientName":"Eli","PatientSurname":"Veliyev","Room":{"Number":1,"RoomType":1,"IsEmty":true},"Price":300.0,"DoctorProfit":0.0,"Categoria":4,"DateBegin":"2021-01-25T23:18:00","DateEnd":"2021-01-25T23:59:00","UsingDevice":[],"Results":null,"UsingMedicine":[],"Recept":[],"Status":2,"Diagnosis":null},{"Id":"1198ec15-8eac-4ee9-887f-9938a26d1fd9","PatientDescription":"Disim agriyir","DrName":"Muradxan","PatientId":"4035fd9e-55a8-4b06-ac4e-741f7aba86eb","PatientName":"Eli","PatientSurname":"Veliyev","Room":{"Number":2,"RoomType":1,"IsEmty":true},"Price":300.0,"DoctorProfit":0.0,"Categoria":4,"DateBegin":"2021-01-19T10:00:00","DateEnd":"2021-01-19T23:00:00","UsingDevice":[{"IsBusy":false,"Name":"aa","Profit":15.0},{"IsBusy":false,"Name":"bb","Profit":15.0}],"Results":null,"UsingMedicine":[],"Recept":[],"Status":4,"Diagnosis":null},{"Id":"e279c014-bc6d-4dab-8c17-a120e448bef3","PatientDescription":"Disim agriyir","DrName":"Qasim","PatientId":"4035fd9e-55a8-4b06-ac4e-741f7aba86eb","PatientName":"Eli","PatientSurname":"Veliyev","Room":{"Number":2,"RoomType":1,"IsEmty":true},"Price":300.0,"DoctorProfit":0.0,"Categoria":4,"DateBegin":"2021-01-19T10:00:00","DateEnd":"2021-01-19T23:00:00","UsingDevice":[{"IsBusy":false,"Name":"zz","Profit":15.0},{"IsBusy":false,"Name":"qq","Profit":15.0}],"Results":null,"UsingMedicine":[],"Recept":[],"Status":4,"Diagnosis":null},{"Id":"7f386c22-3286-4787-8fae-97fa5c1213db","PatientDescription":null,"DrName":"Arif","PatientId":"9a2b9b3c-3f44-44a3-bb7b-125a6d3c26ea","PatientName":"Eli","PatientSurname":"Veliyev","Room":{"Number":0,"RoomType":0,"IsEmty":true},"Price":120.0,"DoctorProfit":0.0,"Categoria":0,"DateBegin":"2021-01-28T12:00:00","DateEnd":"2021-01-28T13:00:00","UsingDevice":[],"Results":null,"UsingMedicine":[],"Recept":[],"Status":3,"Diagnosis":null},{"Id":"4bcd1e11-d932-4275-8a13-91b1ae33ec44","PatientDescription":null,"DrName":"samur","PatientId":"83789f4e-223e-4fd1-98f7-8784d4e6e5ec","PatientName":"zabil","PatientSurname":"haciyev","Room":{"Number":4,"RoomType":0,"IsEmty":true},"Price":0.0,"DoctorProfit":0.0,"Categoria":2,"DateBegin":"2021-01-28T04:56:00","DateEnd":"2021-01-28T06:56:00","UsingDevice":[],"Results":null,"UsingMedicine":[],"Recept":[{"MedicineName":"Aspirin","Note":"Yimekden soram "},{"MedicineName":"Kokoaa","Note":"Yimekden 1 deq 2 san evvel"}],"Status":4,"Diagnosis":"Ay daaaaaa"},{"Id":"5599a000-1130-4acc-bbed-43cf97c002e8","PatientDescription":"asdasdasd","DrName":"samur","PatientId":"1d4f3ad2-0485-4e29-8a43-8617f032cd40","PatientName":"zabil","PatientSurname":"haciyev","Room":{"Number":3,"RoomType":1,"IsEmty":true},"Price":0.0,"DoctorProfit":0.0,"Categoria":1,"DateBegin":"2021-01-28T05:33:00","DateEnd":"2021-01-28T06:33:00","UsingDevice":[{"IsBusy":true,"Name":"Needles","Profit":0.0},{"IsBusy":true,"Name":"Catheters","Profit":0.0}],"Results":null,"UsingMedicine":[{"Price":2.68,"Name":"acetaminophen and codeine","Count":4,"IsEnable":false},{"Price":20.35,"Name":"albuterol aerosol","Count":4,"IsEnable":false}],"Recept":[],"Status":4,"Diagnosis":null},{"Id":"be7e3ad0-2140-4737-89ff-03b3298e217d","PatientDescription":null,"DrName":"samur","PatientId":"4c75f851-812f-4ba7-bdf0-96a635ff1a49","PatientName":"zabil","PatientSurname":"haciyev","Room":{"Number":2,"RoomType":2,"IsEmty":true},"Price":0.0,"DoctorProfit":0.0,"Categoria":0,"DateBegin":"2021-01-28T12:57:00","DateEnd":"2021-01-28T14:57:00","UsingDevice":[{"IsBusy":true,"Name":"Crp","Profit":0.0},{"IsBusy":true,"Name":"Syringes","Profit":0.0}],"Results":null,"UsingMedicine":[{"Price":2.72,"Name":"spasmalgon","Count":4,"IsEnable":true},{"Price":20.35,"Name":"albuterol aerosol","Count":4,"IsEnable":false}],"Recept":[],"Status":5,"Diagnosis":null},{"Id":"476311f2-3da0-4b16-be9e-ff2e175ac5c2","PatientDescription":null,"DrName":"samur","PatientId":"065aba1e-2293-4080-affa-3e9c70606746","PatientName":"Mehemmed","PatientSurname":"Esgerli","Room":{"Number":2,"RoomType":2,"IsEmty":true},"Price":0.0,"DoctorProfit":0.0,"Categoria":0,"DateBegin":"2021-02-04T16:03:00","DateEnd":"2021-02-04T18:03:00","UsingDevice":[{"IsBusy":false,"Name":"Crp","Profit":0.0},{"IsBusy":false,"Name":"Syringes","Profit":0.0}],"Results":null,"UsingMedicine":[{"Price":2.72,"Name":"spasmalgon","Count":4,"IsEnable":true},{"Price":20.35,"Name":"albuterol aerosol","Count":4,"IsEnable":false}],"Recept":[],"Status":0,"Diagnosis":null},{"Id":"9322a48c-7dad-464d-9d61-fbfd0e8bc439","PatientDescription":"Agil disi agriyir ","DrName":"samur","PatientId":"065aba1e-2293-4080-affa-3e9c70606746","PatientName":"Mehemmed","PatientSurname":"Esgerli","Room":{"Number":2,"RoomType":2,"IsEmty":true},"Price":0.0,"DoctorProfit":0.0,"Categoria":0,"DateBegin":"2021-01-28T22:00:00","DateEnd":"2021-01-29T00:00:00","UsingDevice":[{"IsBusy":false,"Name":"Crp","Profit":0.0},{"IsBusy":false,"Name":"Syringes","Profit":0.0}],"Results":null,"UsingMedicine":[{"Price":2.72,"Name":"spasmalgon","Count":4,"IsEnable":true},{"Price":20.35,"Name":"albuterol aerosol","Count":4,"IsEnable":false}],"Recept":[],"Status":2,"Diagnosis":null},{"Id":"0862866e-b4b1-4945-ba40-636b793607e1","PatientDescription":null,"DrName":"samur","PatientId":"ffd7d7fc-3086-4866-86c9-b14482c4d8ab","PatientName":"Mehemmed","PatientSurname":"Esgerli","Room":{"Number":2,"RoomType":2,"IsEmty":true},"Price":0.0,"DoctorProfit":0.0,"Categoria":0,"DateBegin":"2021-01-28T21:46:00","DateEnd":"2021-01-28T23:46:00","UsingDevice":[{"IsBusy":true,"Name":"Crp","Profit":0.0},{"IsBusy":true,"Name":"Syringes","Profit":0.0}],"Results":null,"UsingMedicine":[{"Price":2.72,"Name":"spasmalgon","Count":4,"IsEnable":true},{"Price":20.35,"Name":"albuterol aerosol","Count":4,"IsEnable":false}],"Recept":[{"MedicineName":"spasmalqon","Note":"2 defe yemek qabaq"}],"Status":4,"Diagnosis":"very smart "},{"Id":"5a77b9cb-428f-4287-9e67-8db2f44b1d71","PatientDescription":null,"DrName":"samur","PatientId":"85c7840a-5988-426e-8cae-61480f59ead0","PatientName":"Ayxan","PatientSurname":"Axundov","Room":{"Number":3,"RoomType":1,"IsEmty":true},"Price":0.0,"DoctorProfit":0.0,"Categoria":1,"DateBegin":"2021-02-18T13:00:00","DateEnd":"2021-02-18T14:00:00","UsingDevice":[{"IsBusy":false,"Name":"Needles","Profit":0.0},{"IsBusy":false,"Name":"Catheters","Profit":0.0}],"Results":null,"UsingMedicine":[{"Price":2.68,"Name":"acetaminophen and codeine","Count":4,"IsEnable":false},{"Price":20.35,"Name":"albuterol aerosol","Count":4,"IsEnable":false}],"Recept":[],"Status":0,"Diagnosis":null}]